[
    {
        "icon": "../images/experience/olxgroup_dark_bg.png",
        "institution": "OLX Group",
        "title": "Backend Software Engineer",
        "website": "https://www.olxgroup.com/",
        "location": "Lisbon, Portugal",
        "period": "01/2022 - Present",
        "responsabilities": "",
        "stack": ""
    },
    {
        "icon": "../images/experience/olxgroup_dark_bg.png",
        "institution": "OLX Group",
        "title": "Software Engineer Trainee",
        "website": "https://www.olxgroup.com/",
        "location": "Lisbon, Portugal",
        "period": " 06/2021 - 01/2022",
        "responsabilities": "",
        "stack": ""
    },
    {
        "icon": "../images/experience/blaua_ai.png",
        "institution": "Blaua",
        "title": "Software Engineer",
        "website": "https://www.linkedin.com/company/blaua/",
        "period": "03/2021 - 04/2021",
        "responsabilities": "",
        "stack": ""
    },
    {
        "icon": "../images/experience/deloitte.png",
        "institution": "Deloitte",
        "title": "Summer Intern",
        "website": "https://www2.deloitte.com/pt/pt.html",
        "location": "Lisbon, Portugal",
        "period": "06/2018 - 07/2018",
        "responsabilities": "",
        "stack": ""
    }
]